Workbook
Name aporte: APP!$D$17
Name patrimonio: APP!$D$20
Name qtd_anos: APP!$D$18
Name rendimento_carteira: APP!$D$13
Name salario: APP!$D$12
Name sugestao_investimento: APP!$D$14
Name taxa_mensal: APP!$D$19

Sheet APP
B11: CONFIGURAÇÕES
B12: Salário | D12: 2000
B13: Rendimento Carteira | D13: 0.006
B14: Sugestão de Investimento (30%) | D14: =D12*30%
B16: INVESTIMENTO MENSAL
B17: Quanto investir por mês ? | D17: 200
B18: Por Quantos Anos ? | D18: 5
B19: Taxa de Rendimento mensal ? | D19: 0.01079
B20: Patrimônio acumulado ? | D20: =FV(taxa_mensal,qtd_anos*12,aporte*-1)
B21: Dividendos Mensais ? | D21: =patrimonio*rendimento_carteira
B23: Cenários | D23: Dividendo
A24: 2 | B24: Quanto em 2 Anos ? | C24: =FV($D$19,$A24*12,$D$17*-1) | D24: =C24*rendimento_carteira
A25: 5 | B25: Quanto em 5 Anos ? | C25: =FV($D$19,$A25*12,$D$17*-1) | D25: =C25*rendimento_carteira
A26: 10 | B26: Quanto em 10 Anos ? | C26: =FV($D$19,$A26*12,$D$17*-1) | D26: =C26*rendimento_carteira
A27: 20 | B27: Quanto em 20 Anos ? | C27: =FV($D$19,$A27*12,$D$17*-1) | D27: =C27*rendimento_carteira
A28: 30 | B28: Quanto em 30 Anos ? | C28: =FV($D$19,$A28*12,$D$17*-1) | D28: =C28*rendimento_carteira
B32: PERFIL | C32: Moderado
B33: VALOR A SER INVESTIDO POR MÊS | C33: =aporte
B35: TIPO DE FII | C35: Percentual Sugerido | D35: Valores
B36: PAPEL | C36: =VLOOKUP($C$32&"-"&B36,Planilha2!$A:$D,4,FALSE) | D36: =C36*$C$33
B37: TIJOLO | C37: =VLOOKUP($C$32&"-"&B37,Planilha2!$A:$D,4,FALSE) | D37: =C37*$C$33
B38: HÍBRIDOS | C38: =VLOOKUP($C$32&"-"&B38,Planilha2!$A:$D,4,FALSE) | D38: =C38*$C$33
B39: FOFs | C39: =VLOOKUP($C$32&"-"&B39,Planilha2!$A:$D,4,FALSE) | D39: =C39*$C$33
B40: DESENVOLVIMENTO | C40: =VLOOKUP($C$32&"-"&B40,Planilha2!$A:$D,4,FALSE) | D40: =C40*$C$33
B41: HOTELARIAS | C41: =VLOOKUP($C$32&"-"&B41,Planilha2!$A:$D,4,FALSE) | D41: =C41*$C$33
D42: =SUM(D36:D41)

Sheet Planilha2
A2: CHAVE | B2: PERFIL | C2: TIPO DE FII | D2: %
A3: =B3&"-"&C3 | B3: Conservador | C3: PAPEL | D3: 0.3 | H3: %
A4: =B4&"-"&C4 | B4: Conservador | C4: TIJOLO | D4: 0.5 | G4: Moderado-TIJOLO | H4: =VLOOKUP(G4,$A:$D,4,FALSE)
A5: =B5&"-"&C5 | B5: Conservador | C5: HÍBRIDOS | D5: 0.1
A6: =B6&"-"&C6 | B6: Conservador | C6: FOFs | D6: 0.1
A7: =B7&"-"&C7 | B7: Conservador | C7: DESENVOLVIMENTO | D7: 0
A8: =B8&"-"&C8 | B8: Conservador | C8: HOTELARIAS | D8: 0
A9: =B9&"-"&C9 | B9: Moderado | C9: PAPEL | D9: 0.32
A10: =B10&"-"&C10 | B10: Moderado | C10: TIJOLO | D10: 0.35
A11: =B11&"-"&C11 | B11: Moderado | C11: HÍBRIDOS | D11: 0.08
A12: =B12&"-"&C12 | B12: Moderado | C12: FOFs | D12: 0.05
A13: =B13&"-"&C13 | B13: Moderado | C13: DESENVOLVIMENTO | D13: 0.1
A14: =B14&"-"&C14 | B14: Moderado | C14: HOTELARIAS | D14: 0.1
A15: =B15&"-"&C15 | B15: Agressivo | C15: PAPEL | D15: 0.5
A16: =B16&"-"&C16 | B16: Agressivo | C16: TIJOLO | D16: 0.1
... A20: =B20&"-"&C20 | B20: Agressivo | C20: HOTELARIAS | D20: 0.1

Sheet DOCUMENTAÇÃO
A1: Simulador de Investimentos em Fundos Imobiliários (FIIs)
A3: Descrição:
A4: Esta planilha permite simular investimentos mensais em FIIs, calculando patrimônio futuro e dividendos.
A6: Como usar:
A7: 1. Informe seu salário.
A8: 2. Defina quanto deseja investir por mês.
A9: 3. Escolha o período (anos) e taxa de rendimento.
A10: 4. Visualize o patrimônio acumulado e dividendos.
A12: Fórmulas principais:
A13: FV -> calcula valor futuro.
A14: Dividendos -> patrimônio * rendimento mensal.
